pydocgenerator/__init__.py
pydocgenerator/pydoc.py
pydcogenerator-0.1.0.dist-info/LICENSE
pydcogenerator-0.1.0.dist-info/METADATA
pydcogenerator-0.1.0.dist-info/WHEEL
pydcogenerator-0.1.0.dist-info/top_level.txt
pydcogenerator-0.1.0.dist-info/RECORD
