Metadata-Version: 2.1
Name: pydcogenerator
Version: 0.1.0
Summary: A library for generating docstring for python programms.
Author-email: Rijin <rijinraj856@example.com>, Amal <amal76735@example.com>, Yadhu <yadhu2309856@example.com>
Project-URL: Homepage, https://github.com/RijinRaju/PyDocGenerator
Project-URL: Issues, https://github.com/RijinRaju/PyDocGenerator/issues
Classifier: Programming Language :: Python :: 3
Classifier: License :: OSI Approved :: MIT License
Classifier: Operating System :: OS Independent
Requires-Python: >=3.8
License-File: LICENSE
